streamlit_tile/__init__.py
streamlit_tile/example.py
streamlit_tile/frontend/build/asset-manifest.json
streamlit_tile/frontend/build/index.html
streamlit_tile/frontend/build/static/js/main.746fdace.js
streamlit_tile/frontend/build/static/js/main.746fdace.js.LICENSE.txt
streamlit_tile/frontend/build/static/js/main.746fdace.js.map
streamlit_tile-4.1.0.dist-info/licenses/LICENSE
streamlit_tile-4.1.0.dist-info/METADATA
streamlit_tile-4.1.0.dist-info/WHEEL
streamlit_tile-4.1.0.dist-info/top_level.txt
streamlit_tile-4.1.0.dist-info/RECORD
