Metadata-Version: 2.4
Name: streamlit-tile
Version: 4.1.0
Summary: A customizable tile component for Streamlit apps
Home-page: https://github.com/sakunaharinda/streamlit-tile
Author: Sakuna Jayasundara
Author-email: sakunaj1996@gmail.com
Classifier: Programming Language :: Python :: 3
Classifier: License :: OSI Approved :: MIT License
Classifier: Operating System :: OS Independent
Requires-Python: >=3.7
License-File: LICENSE
Requires-Dist: streamlit
Dynamic: author
Dynamic: author-email
Dynamic: classifier
Dynamic: description
Dynamic: description-content-type
Dynamic: home-page
Dynamic: license-file
Dynamic: requires-dist
Dynamic: requires-python
Dynamic: summary
